Metadata-Version: 1.0
Name: gaus-bin-dists
Version: 0.11
Summary: Gaussian and Binomial distributions
Home-page: UNKNOWN
Author: Robert Knight
Author-email: robertpknight@hotmail.com
License: UNKNOWN
Platform: UNKNOWN
